CHANGES.txt
LICENSE.txt
README.rst
setup.py
dist/inifaction-0.1.tar.gz
examples/example.ini
inifaction/__init__.py
inifaction/api.py
inifaction/config.py
inifaction/items.py
inifaction/main.py
inifaction/setup.py
inifaction/template.ini
inifaction/validation.ini
inifaction.egg-info/PKG-INFO
inifaction.egg-info/SOURCES.txt
inifaction.egg-info/dependency_links.txt
inifaction.egg-info/entry_points.txt
inifaction.egg-info/not-zip-safe
inifaction.egg-info/requires.txt
inifaction.egg-info/top_level.txt
tests/config.ini
tests/config.py
tests/tests.py