Metadata-Version: 1.1
Name: inifaction
Version: 0.1
Summary: Manage your Webfaction settings in a per project basis from an INI style file.
Home-page: https://lagunak.gisa-elkartea.org/projects/inifaction/
Author: Unai Zalakain (GISA)
Author-email: unai@gisa-elkartea.org
License: LICENSE.txt
Keywords: webfaction,api,xml,rpc,ini,configuration
Platform: UNKNOWN
Classifier: Development Status :: 5 - Production/Stable
Classifier: Environment :: Console
Classifier: Intended Audience :: System Administrators
Classifier: License :: OSI Approved :: GNU General Public License (GPL)
Classifier: Natural Language :: English
Classifier: Operating System :: OS Independent
Classifier: Programming Language :: Python :: 2.6
Classifier: Topic :: Utilities
